py_mcumgr_client-0.0.5rc1.dist-info/METADATA
py_mcumgr_client-0.0.5rc1.dist-info/WHEEL
py_mcumgr_client/__init__.py
py_mcumgr_client/py_mcumgr_client.pypy39-pp73-x86_64-linux-gnu.so
py_mcumgr_client-0.0.5rc1.dist-info/RECORD
