Metadata-Version: 2.3
Name: py-mcumgr-client
Version: 0.0.5rc1
Classifier: Programming Language :: Rust
Classifier: Programming Language :: Python :: Implementation :: CPython
Classifier: Programming Language :: Python :: Implementation :: PyPy
Summary: Python bindings for the rust library mcumgr-client
Author: Adrien Bruant
License: Apache-2.0
Requires-Python: >=3.8
Project-URL: Repository, https://github.com/comap-smart-home/py-mcumgr-client
